deriver/__init__.py
deriver/api.py
deriver/brics_mating_rules.py
deriver/child_filter.py
deriver/clean_frag_db.py
deriver/config.py
deriver/fragment.py
deriver/fragment_caches.py
deriver/fragment_index.py
deriver/fragment_queries.py
deriver/jensen_crossover.py
deriver/jensen_mutate.py
deriver/jensen_selfies_crossover.py
deriver/jensen_selfies_mutate.py
deriver/lib_read.py
deriver/mate.py
deriver/selfies_methods.py
deriver/util.py
deriver/data/alert_collection.csv
deriver-2.9.0.dist-info/LICENSE
deriver-2.9.0.dist-info/METADATA
deriver-2.9.0.dist-info/WHEEL
deriver-2.9.0.dist-info/top_level.txt
deriver-2.9.0.dist-info/RECORD
