Metadata-Version: 2.1
Name: deriver
Version: 2.9.0
Summary: Deriver: for all your molecule generation needs.
Home-page: https://github.com/cyclica/deriver
License: All Rights Reserved Cyclica Inc.
License-File: LICENSE
Requires-Dist: selfies (==1.0.1)
Requires-Dist: peewee (>=3.9.3)
Requires-Dist: numpy (>=1.16.3)
Requires-Dist: crem (==0.2.4)
Requires-Dist: loguru (==0.4.1)
Requires-Dist: pandas (>=1.0.*)
